  {
    "id": "PSY_magi_magic_revolver_ver3",
    "copy-from": "pistol_revolver",
    "looks_like": "sw_619",
    "type": "GUN",
    "name": "マナカートリッジ専用拳銃 トリア[MWMI]",
    "extend": { "flags": [ "MAGIC_FOCUS" ] },
    "description": "魔法使いの為に設計されたマナカートリッジ弾専用拳銃 トリアです。これを使いこなせるようになれば、あなたも一人前の魔法使いです。",
    "weight": "935 g",
    "volume": "500 ml",
    "price": 30000,
    "to_hit": -2,
    "bashing": 8,
    "material": [ "steel", "wood","copper" ],
    "symbol": "(",
    "color": "dark_gray",
    "ammo": "PSY_magi_9x19_magic",
    "range": 1,
    "dispersion": 340,
    "durability": 9,
    "clip_size": 6,
    "pocket_data": [ 
      { "pocket_type": "MAGAZINE",
        "holster": true, 
        "rigid": true, 
        "ammo_restriction": { "PSY_magi_9x19_magic": 6 },
        "allowed_speedloaders": [ "PSY_magi_9mm_magic_speedloader6" ]
      }
    ],
    "valid_mod_locations": [
      [ "accessories", 2 ],
      [ "barrel", 1 ],
      [ "bore", 1 ],
      [ "grip", 1 ],
      [ "mechanism", 4 ],
      [ "rail", 1 ],
      [ "sights", 1 ],
      [ "stock", 1 ],
      [ "underbarrel", 1 ]
    ]
  }